soc/__init__.py
soc/helpers.py
soc/request.py
soc/soc.py
soc/socket_view.py
tests/__init__.py
tests/test_soq.py
soc-0.0.1.dist-info/LICENSE
soc-0.0.1.dist-info/METADATA
soc-0.0.1.dist-info/WHEEL
soc-0.0.1.dist-info/top_level.txt
soc-0.0.1.dist-info/RECORD
