Metadata-Version: 2.1
Name: soc
Version: 0.0.1
Summary: A lightweight websocket micro framework
Home-page: https://github.com/Julian-Nash/soc
Author: Julian Nash
Author-email: julianjamesnash@gmail.com
License: UNKNOWN
Project-URL: Bug Tracker, https://github.com/Julian-Nash/soc
Project-URL: Documentation, https://github.com/Julian-Nash/soc
Project-URL: Source Code, https://github.com/Julian-Nash/soc
Keywords: websocket micro framework
Platform: UNKNOWN
Classifier: Intended Audience :: Developers
Classifier: License :: OSI Approved :: MIT License
Classifier: Programming Language :: Python :: 3.6
Classifier: Programming Language :: Python :: 3.7
Classifier: Programming Language :: Python :: 3.8
Requires-Dist: websockets (==8.1)
